feigenbaum/__init__.py
feigenbaum/generation.py
feigenbaum-0.1.0.dist-info/METADATA
feigenbaum-0.1.0.dist-info/WHEEL
feigenbaum-0.1.0.dist-info/top_level.txt
feigenbaum-0.1.0.dist-info/RECORD
