Metadata-Version: 2.1
Name: feigenbaum
Version: 0.1.0
Summary: Feigenbaum chart generator
Home-page: UNKNOWN
Author: Max Simmons
Author-email: max@mxsmns.net
License: UNKNOWN
Platform: UNKNOWN
